README.md
setup.py
MT5pytrader/__init__.py
MT5pytrader/pytrader.py
MT5pytrader.egg-info/PKG-INFO
MT5pytrader.egg-info/SOURCES.txt
MT5pytrader.egg-info/dependency_links.txt
MT5pytrader.egg-info/not-zip-safe
MT5pytrader.egg-info/requires.txt
MT5pytrader.egg-info/top_level.txt