Metadata-Version: 2.1
Name: MT5pytrader
Version: 0.61
Summary: MT5pytrader
Home-page: https://github.com/raimiazeez26/MT5pytrader
Author: Raimi Azeez Babatunde
Author-email: raimiazeez26@gmail.com
License: MIT
Keywords: MT5pytrader,python,Metatrader5,MT5,algotrading,autroading
Platform: UNKNOWN
